c2pa/__init__.py
c2pa/build.py
c2pa/c2pa.py
c2pa/lib.py
c2pa/libs/libc2pa_c.dylib
c2pa/libs/libc2pa_c.dylib.dSYM.zip
c2pa_python-0.28.0.dist-info/METADATA
c2pa_python-0.28.0.dist-info/WHEEL
c2pa_python-0.28.0.dist-info/entry_points.txt
c2pa_python-0.28.0.dist-info/top_level.txt
c2pa_python-0.28.0.dist-info/RECORD
