Metadata-Version: 2.1
Name: c2pa-python
Version: 0.28.0
Summary: Python bindings for the C2PA Content Authenticity Initiative (CAI) library
Author-email: Gavin Peacock <gvnpeacock@adobe.com>, Tania Mathern <mathern@adobe.com>
Maintainer-email: Gavin Peacock <gpeacock@adobe.com>
License: MIT OR Apache-2.0
Project-URL: homepage, https://contentauthenticity.org
Project-URL: repository, https://github.com/contentauth/c2pa-python
Classifier: Programming Language :: Python :: 3
Classifier: Operating System :: MacOS
Classifier: Operating System :: POSIX :: Linux
Classifier: Operating System :: Microsoft :: Windows
Requires-Python: >=3.10
Requires-Dist: wheel >=0.41.2
Requires-Dist: setuptools >=68.0.0
Requires-Dist: toml >=0.10.2
Requires-Dist: pytest >=7.4.0
Requires-Dist: cryptography >=41.0.0
Requires-Dist: requests >=2.0.0
